<?xml version="1.0" encoding="UTF-8"?>
<!DOCTYPE mapper PUBLIC "-//mybatis.org//DTD Mapper 3.0//EN" "http://mybatis.org/dtd/mybatis-3-mapper.dtd">
<mapper namespace="com.bizwink.persistence.ColumnMapper">
    <resultMap id="BaseResultMap" type="com.bizwink.po.Column">
        <!--
          WARNING - @mbggenerated
          This element is automatically generated by MyBatis Generator, do not modify.
        -->
        <id column="ID" jdbcType="DECIMAL" property="ID" />
        <result column="SITEID" jdbcType="DECIMAL" property="SITEID" />
        <result column="PARENTID" jdbcType="DECIMAL" property="PARENTID" />
        <result column="ORDERID" jdbcType="DECIMAL" property="ORDERID" />
        <result column="CNAME" jdbcType="VARCHAR" property="CNAME" />
        <result column="ENAME" jdbcType="VARCHAR" property="ENAME" />
        <result column="DIRNAME" jdbcType="VARCHAR" property="DIRNAME" />
        <result column="EDITOR" jdbcType="VARCHAR" property="EDITOR" />
        <result column="EXTNAME" jdbcType="VARCHAR" property="EXTNAME" />
        <result column="CREATEDATE" jdbcType="DATE" property="CREATEDATE" />
        <result column="LASTUPDATED" jdbcType="DATE" property="LASTUPDATED" />
        <result column="ISDEFINEATTR" jdbcType="DECIMAL" property="ISDEFINEATTR" />
        <result column="HASARTICLEMODEL" jdbcType="DECIMAL" property="HASARTICLEMODEL" />
        <result column="ISAUDITED" jdbcType="DECIMAL" property="ISAUDITED" />
        <result column="ISPRODUCT" jdbcType="DECIMAL" property="ISPRODUCT" />
        <result column="ISPUBLISHMORE" jdbcType="DECIMAL" property="ISPUBLISHMORE" />
        <result column="LANGUAGETYPE" jdbcType="DECIMAL" property="LANGUAGETYPE" />
        <result column="COLUMNDESC" jdbcType="VARCHAR" property="COLUMNDESC" />
        <result column="XMLTEMPLATE" jdbcType="VARCHAR" property="XMLTEMPLATE" />
        <result column="CONTENTSHOWTYPE" jdbcType="DECIMAL" property="CONTENTSHOWTYPE" />
        <result column="ISRSS" jdbcType="DECIMAL" property="ISRSS" />
        <result column="GETRSSARTICLETIME" jdbcType="DECIMAL" property="GETRSSARTICLETIME" />
        <result column="ARCHIVINGRULES" jdbcType="DECIMAL" property="ARCHIVINGRULES" />
        <result column="USEARTICLETYPE" jdbcType="DECIMAL" property="USEARTICLETYPE" />
        <result column="ISTYPE" jdbcType="DECIMAL" property="ISTYPE" />
        <result column="USERFLAG" jdbcType="DECIMAL" property="USERFLAG" />
        <result column="USERLEVEL" jdbcType="DECIMAL" property="USERLEVEL" />
        <result column="SHAREFLAG" jdbcType="DECIMAL" property="SHAREFLAG" />
        <result column="XMLTYPE" jdbcType="VARCHAR" property="XMLTYPE" />
        <result column="ARTICLECOUNT" jdbcType="DECIMAL" property="ARTICLECOUNT" />
        <result column="PUBLICFLAG" jdbcType="DECIMAL" property="PUBLICFLAG" />
        <result column="TITLEPIC" jdbcType="VARCHAR" property="TITLEPIC" />
        <result column="VTITLEPIC" jdbcType="VARCHAR" property="VTITLEPIC" />
        <result column="SOURCEPIC" jdbcType="VARCHAR" property="SOURCEPIC" />
        <result column="AUTHORPIC" jdbcType="VARCHAR" property="AUTHORPIC" />
        <result column="CONTENTPIC" jdbcType="VARCHAR" property="CONTENTPIC" />
        <result column="SPECIALPIC" jdbcType="VARCHAR" property="SPECIALPIC" />
        <result column="PRODUCTPIC" jdbcType="VARCHAR" property="PRODUCTPIC" />
        <result column="PRODUCTSMALLPIC" jdbcType="VARCHAR" property="PRODUCTSMALLPIC" />
        <result column="TS_PIC" jdbcType="VARCHAR" property="TS_PIC" />
        <result column="S_PIC" jdbcType="VARCHAR" property="s_PIC" />
        <result column="MS_PIC" jdbcType="VARCHAR" property="MS_PIC" />
        <result column="M_PIC" jdbcType="VARCHAR" property="m_PIC" />
        <result column="ML_PIC" jdbcType="VARCHAR" property="ML_PIC" />
        <result column="L_PIC" jdbcType="VARCHAR" property="l_PIC" />
        <result column="TL_PIC" jdbcType="VARCHAR" property="TL_PIC" />
    </resultMap>

    <resultMap id="ResultIDMap" type="com.bizwink.po.ColumnIDS">
        <!--
          WARNING - @mbggenerated
          This element is automatically generated by MyBatis Generator, do not modify.
        -->
        <id column="ID" jdbcType="DECIMAL" property="ID" />
        <result column="SITEID" jdbcType="DECIMAL" property="SITEID" />
        <result column="PARENTID" jdbcType="DECIMAL" property="PARENTID" />
    </resultMap>

    <sql id="Base_Column_List">
        <!--
          WARNING - @mbggenerated
          This element is automatically generated by MyBatis Generator, do not modify.
        -->
        ID, SITEID, PARENTID, ORDERID, CNAME, ENAME, DIRNAME, EDITOR, EXTNAME, CREATEDATE,
        LASTUPDATED, ISDEFINEATTR, HASARTICLEMODEL, ISAUDITED, ISPRODUCT, ISPUBLISHMORE,
        LANGUAGETYPE, COLUMNDESC, XMLTEMPLATE, CONTENTSHOWTYPE, ISRSS, GETRSSARTICLETIME,
        ARCHIVINGRULES, USEARTICLETYPE, ISTYPE, USERFLAG, USERLEVEL, SHAREFLAG, XMLTYPE,
        ARTICLECOUNT, PUBLICFLAG, TITLEPIC, VTITLEPIC, SOURCEPIC, AUTHORPIC, CONTENTPIC,
        SPECIALPIC, PRODUCTPIC, PRODUCTSMALLPIC, TS_PIC, S_PIC, MS_PIC, M_PIC, ML_PIC, L_PIC,
        TL_PIC
    </sql>

    <select id="selectByPrimaryKey" parameterType="java.math.BigDecimal" resultMap="BaseResultMap">
        <!--
          WARNING - @mbggenerated
          This element is automatically generated by MyBatis Generator, do not modify.
        -->
        select
        <include refid="Base_Column_List" />
        from TBL_COLUMN
        where ID = #{ID,jdbcType=DECIMAL}
    </select>

    <select id="getColumnsBySiteid" parameterType="java.math.BigDecimal" resultMap="BaseResultMap">
        <!--
          WARNING - @mbggenerated
          This element is automatically generated by MyBatis Generator, do not modify.
        -->
        select
        <include refid="Base_Column_List" />
        from TBL_COLUMN
        where SITEID = #{SITEID,jdbcType=DECIMAL}
    </select>

    <select id="getSubColumnsByParentID" parameterType="java.math.BigDecimal" resultMap="BaseResultMap">
        <!--
          WARNING - @mbggenerated
          This element is automatically generated by MyBatis Generator, do not modify.
        -->
        select
        <include refid="Base_Column_List" />
        from TBL_COLUMN
        where PARENTID = #{PARENTID,jdbcType=DECIMAL}
    </select>

    <select id="getSubColumnIdsByParentID" parameterType="java.math.BigDecimal" resultMap="ResultIDMap">
        <!--
          WARNING - @mbggenerated
          This element is automatically generated by MyBatis Generator, do not modify.
        -->
        select ID,SITEID,PARENTID from TBL_COLUMN
        where PARENTID = #{PARENTID,jdbcType=DECIMAL}
    </select>

    <select id="getSubColumnsByParentIDs" resultMap="BaseResultMap">
        <!--
          WARNING - @mbggenerated
          This element is automatically generated by MyBatis Generator, do not modify.
        -->
        select
        <include refid="Base_Column_List" />
        from tbl_column where parentid = 50839
    </select>


    <select id="getColumnsNotIncludeRootColumnBySiteidOrderByOrderID" parameterType="java.math.BigDecimal" resultMap="BaseResultMap">
        <!--
          WARNING - @mbggenerated
          This element is automatically generated by MyBatis Generator, do not modify.
        -->
        SELECT * FROM tbl_column where SITEID = #{SITEID,jdbcType=DECIMAL} and PARENTID > 0 order by ORDERID desc
    </select>

    <select id="getRootColumnBySiteid" parameterType="java.math.BigDecimal" resultMap="BaseResultMap">
        <!--
          WARNING - @mbggenerated
          This element is automatically generated by MyBatis Generator, do not modify.
        -->
        select
        <include refid="Base_Column_List" />
        from TBL_COLUMN
        where SITEID = #{SITEID,jdbcType=DECIMAL}  and PARENTID = 0
    </select>

    <select id="getColumnCount" parameterType="java.math.BigDecimal" resultType="java.lang.Integer">
        SELECT count(*) FROM tbl_column where SITEID = #{SITEID,jdbcType=DECIMAL}
    </select>

    <select id="getRootColumnIdBySiteid" parameterType="java.math.BigDecimal" resultType="java.lang.Integer">
        select min(id)  from TBL_COLUMN where SITEID = #{SITEID,jdbcType=DECIMAL}
    </select>

    <delete id="deleteByPrimaryKey" parameterType="java.math.BigDecimal">
        <!--
          WARNING - @mbggenerated
          This element is automatically generated by MyBatis Generator, do not modify.
        -->
        delete from TBL_COLUMN
        where ID = #{ID,jdbcType=DECIMAL}
    </delete>

    <select id="getColumnMainKey" resultType="java.math.BigDecimal">
        select tbl_column_id.NEXTVAL from dual
    </select>

    <insert id="insert" parameterType="com.bizwink.po.Column">
        <!--
          WARNING - @mbggenerated
          This element is automatically generated by MyBatis Generator, do not modify.
        -->
        insert into TBL_COLUMN (ID, SITEID, PARENTID,
        ORDERID, CNAME, ENAME,
        DIRNAME, EDITOR, EXTNAME,
        CREATEDATE, LASTUPDATED, ISDEFINEATTR,
        HASARTICLEMODEL, ISAUDITED, ISPRODUCT,
        ISPUBLISHMORE, LANGUAGETYPE, COLUMNDESC,
        XMLTEMPLATE, CONTENTSHOWTYPE, ISRSS,
        GETRSSARTICLETIME, ARCHIVINGRULES, USEARTICLETYPE,
        ISTYPE, USERFLAG, USERLEVEL,
        SHAREFLAG, XMLTYPE, ARTICLECOUNT,
        PUBLICFLAG, TITLEPIC, VTITLEPIC,
        SOURCEPIC, AUTHORPIC, CONTENTPIC,
        SPECIALPIC, PRODUCTPIC, PRODUCTSMALLPIC,
        TS_PIC, S_PIC, MS_PIC,
        M_PIC, ML_PIC, L_PIC,
        TL_PIC)
        values (#{ID,jdbcType=DECIMAL}, #{SITEID,jdbcType=DECIMAL}, #{PARENTID,jdbcType=DECIMAL},
        #{ORDERID,jdbcType=DECIMAL}, #{CNAME,jdbcType=VARCHAR}, #{ENAME,jdbcType=VARCHAR},
        #{DIRNAME,jdbcType=VARCHAR}, #{EDITOR,jdbcType=VARCHAR}, #{EXTNAME,jdbcType=VARCHAR},
        #{CREATEDATE,jdbcType=DATE}, #{LASTUPDATED,jdbcType=DATE}, #{ISDEFINEATTR,jdbcType=DECIMAL},
        #{HASARTICLEMODEL,jdbcType=DECIMAL}, #{ISAUDITED,jdbcType=DECIMAL}, #{ISPRODUCT,jdbcType=DECIMAL},
        #{ISPUBLISHMORE,jdbcType=DECIMAL}, #{LANGUAGETYPE,jdbcType=DECIMAL}, #{COLUMNDESC,jdbcType=VARCHAR},
        #{XMLTEMPLATE,jdbcType=VARCHAR}, #{CONTENTSHOWTYPE,jdbcType=DECIMAL}, #{ISRSS,jdbcType=DECIMAL},
        #{GETRSSARTICLETIME,jdbcType=DECIMAL}, #{ARCHIVINGRULES,jdbcType=DECIMAL}, #{USEARTICLETYPE,jdbcType=DECIMAL},
        #{ISTYPE,jdbcType=DECIMAL}, #{USERFLAG,jdbcType=DECIMAL}, #{USERLEVEL,jdbcType=DECIMAL},
        #{SHAREFLAG,jdbcType=DECIMAL}, #{XMLTYPE,jdbcType=VARCHAR}, #{ARTICLECOUNT,jdbcType=DECIMAL},
        #{PUBLICFLAG,jdbcType=DECIMAL}, #{TITLEPIC,jdbcType=VARCHAR}, #{VTITLEPIC,jdbcType=VARCHAR},
        #{SOURCEPIC,jdbcType=VARCHAR}, #{AUTHORPIC,jdbcType=VARCHAR}, #{CONTENTPIC,jdbcType=VARCHAR},
        #{SPECIALPIC,jdbcType=VARCHAR}, #{PRODUCTPIC,jdbcType=VARCHAR}, #{PRODUCTSMALLPIC,jdbcType=VARCHAR},
        #{TS_PIC,jdbcType=VARCHAR}, #{s_PIC,jdbcType=VARCHAR}, #{MS_PIC,jdbcType=VARCHAR},
        #{m_PIC,jdbcType=VARCHAR}, #{ML_PIC,jdbcType=VARCHAR}, #{l_PIC,jdbcType=VARCHAR},
        #{TL_PIC,jdbcType=VARCHAR})
    </insert>
    <insert id="insertSelective" parameterType="com.bizwink.po.Column">
        <!--
          WARNING - @mbggenerated
          This element is automatically generated by MyBatis Generator, do not modify.
        -->
        insert into TBL_COLUMN
        <trim prefix="(" suffix=")" suffixOverrides=",">
            <if test="ID != null">
                ID,
            </if>
            <if test="SITEID != null">
                SITEID,
            </if>
            <if test="PARENTID != null">
                PARENTID,
            </if>
            <if test="ORDERID != null">
                ORDERID,
            </if>
            <if test="CNAME != null">
                CNAME,
            </if>
            <if test="ENAME != null">
                ENAME,
            </if>
            <if test="DIRNAME != null">
                DIRNAME,
            </if>
            <if test="EDITOR != null">
                EDITOR,
            </if>
            <if test="EXTNAME != null">
                EXTNAME,
            </if>
            <if test="CREATEDATE != null">
                CREATEDATE,
            </if>
            <if test="LASTUPDATED != null">
                LASTUPDATED,
            </if>
            <if test="ISDEFINEATTR != null">
                ISDEFINEATTR,
            </if>
            <if test="HASARTICLEMODEL != null">
                HASARTICLEMODEL,
            </if>
            <if test="ISAUDITED != null">
                ISAUDITED,
            </if>
            <if test="ISPRODUCT != null">
                ISPRODUCT,
            </if>
            <if test="ISPUBLISHMORE != null">
                ISPUBLISHMORE,
            </if>
            <if test="LANGUAGETYPE != null">
                LANGUAGETYPE,
            </if>
            <if test="COLUMNDESC != null">
                COLUMNDESC,
            </if>
            <if test="XMLTEMPLATE != null">
                XMLTEMPLATE,
            </if>
            <if test="CONTENTSHOWTYPE != null">
                CONTENTSHOWTYPE,
            </if>
            <if test="ISRSS != null">
                ISRSS,
            </if>
            <if test="GETRSSARTICLETIME != null">
                GETRSSARTICLETIME,
            </if>
            <if test="ARCHIVINGRULES != null">
                ARCHIVINGRULES,
            </if>
            <if test="USEARTICLETYPE != null">
                USEARTICLETYPE,
            </if>
            <if test="ISTYPE != null">
                ISTYPE,
            </if>
            <if test="USERFLAG != null">
                USERFLAG,
            </if>
            <if test="USERLEVEL != null">
                USERLEVEL,
            </if>
            <if test="SHAREFLAG != null">
                SHAREFLAG,
            </if>
            <if test="XMLTYPE != null">
                XMLTYPE,
            </if>
            <if test="ARTICLECOUNT != null">
                ARTICLECOUNT,
            </if>
            <if test="PUBLICFLAG != null">
                PUBLICFLAG,
            </if>
            <if test="TITLEPIC != null">
                TITLEPIC,
            </if>
            <if test="VTITLEPIC != null">
                VTITLEPIC,
            </if>
            <if test="SOURCEPIC != null">
                SOURCEPIC,
            </if>
            <if test="AUTHORPIC != null">
                AUTHORPIC,
            </if>
            <if test="CONTENTPIC != null">
                CONTENTPIC,
            </if>
            <if test="SPECIALPIC != null">
                SPECIALPIC,
            </if>
            <if test="PRODUCTPIC != null">
                PRODUCTPIC,
            </if>
            <if test="PRODUCTSMALLPIC != null">
                PRODUCTSMALLPIC,
            </if>
            <if test="TS_PIC != null">
                TS_PIC,
            </if>
            <if test="s_PIC != null">
                S_PIC,
            </if>
            <if test="MS_PIC != null">
                MS_PIC,
            </if>
            <if test="m_PIC != null">
                M_PIC,
            </if>
            <if test="ML_PIC != null">
                ML_PIC,
            </if>
            <if test="l_PIC != null">
                L_PIC,
            </if>
            <if test="TL_PIC != null">
                TL_PIC,
            </if>
        </trim>
        <trim prefix="values (" suffix=")" suffixOverrides=",">
            <if test="ID != null">
                #{ID,jdbcType=DECIMAL},
            </if>
            <if test="SITEID != null">
                #{SITEID,jdbcType=DECIMAL},
            </if>
            <if test="PARENTID != null">
                #{PARENTID,jdbcType=DECIMAL},
            </if>
            <if test="ORDERID != null">
                #{ORDERID,jdbcType=DECIMAL},
            </if>
            <if test="CNAME != null">
                #{CNAME,jdbcType=VARCHAR},
            </if>
            <if test="ENAME != null">
                #{ENAME,jdbcType=VARCHAR},
            </if>
            <if test="DIRNAME != null">
                #{DIRNAME,jdbcType=VARCHAR},
            </if>
            <if test="EDITOR != null">
                #{EDITOR,jdbcType=VARCHAR},
            </if>
            <if test="EXTNAME != null">
                #{EXTNAME,jdbcType=VARCHAR},
            </if>
            <if test="CREATEDATE != null">
                #{CREATEDATE,jdbcType=DATE},
            </if>
            <if test="LASTUPDATED != null">
                #{LASTUPDATED,jdbcType=DATE},
            </if>
            <if test="ISDEFINEATTR != null">
                #{ISDEFINEATTR,jdbcType=DECIMAL},
            </if>
            <if test="HASARTICLEMODEL != null">
                #{HASARTICLEMODEL,jdbcType=DECIMAL},
            </if>
            <if test="ISAUDITED != null">
                #{ISAUDITED,jdbcType=DECIMAL},
            </if>
            <if test="ISPRODUCT != null">
                #{ISPRODUCT,jdbcType=DECIMAL},
            </if>
            <if test="ISPUBLISHMORE != null">
                #{ISPUBLISHMORE,jdbcType=DECIMAL},
            </if>
            <if test="LANGUAGETYPE != null">
                #{LANGUAGETYPE,jdbcType=DECIMAL},
            </if>
            <if test="COLUMNDESC != null">
                #{COLUMNDESC,jdbcType=VARCHAR},
            </if>
            <if test="XMLTEMPLATE != null">
                #{XMLTEMPLATE,jdbcType=VARCHAR},
            </if>
            <if test="CONTENTSHOWTYPE != null">
                #{CONTENTSHOWTYPE,jdbcType=DECIMAL},
            </if>
            <if test="ISRSS != null">
                #{ISRSS,jdbcType=DECIMAL},
            </if>
            <if test="GETRSSARTICLETIME != null">
                #{GETRSSARTICLETIME,jdbcType=DECIMAL},
            </if>
            <if test="ARCHIVINGRULES != null">
                #{ARCHIVINGRULES,jdbcType=DECIMAL},
            </if>
            <if test="USEARTICLETYPE != null">
                #{USEARTICLETYPE,jdbcType=DECIMAL},
            </if>
            <if test="ISTYPE != null">
                #{ISTYPE,jdbcType=DECIMAL},
            </if>
            <if test="USERFLAG != null">
                #{USERFLAG,jdbcType=DECIMAL},
            </if>
            <if test="USERLEVEL != null">
                #{USERLEVEL,jdbcType=DECIMAL},
            </if>
            <if test="SHAREFLAG != null">
                #{SHAREFLAG,jdbcType=DECIMAL},
            </if>
            <if test="XMLTYPE != null">
                #{XMLTYPE,jdbcType=VARCHAR},
            </if>
            <if test="ARTICLECOUNT != null">
                #{ARTICLECOUNT,jdbcType=DECIMAL},
            </if>
            <if test="PUBLICFLAG != null">
                #{PUBLICFLAG,jdbcType=DECIMAL},
            </if>
            <if test="TITLEPIC != null">
                #{TITLEPIC,jdbcType=VARCHAR},
            </if>
            <if test="VTITLEPIC != null">
                #{VTITLEPIC,jdbcType=VARCHAR},
            </if>
            <if test="SOURCEPIC != null">
                #{SOURCEPIC,jdbcType=VARCHAR},
            </if>
            <if test="AUTHORPIC != null">
                #{AUTHORPIC,jdbcType=VARCHAR},
            </if>
            <if test="CONTENTPIC != null">
                #{CONTENTPIC,jdbcType=VARCHAR},
            </if>
            <if test="SPECIALPIC != null">
                #{SPECIALPIC,jdbcType=VARCHAR},
            </if>
            <if test="PRODUCTPIC != null">
                #{PRODUCTPIC,jdbcType=VARCHAR},
            </if>
            <if test="PRODUCTSMALLPIC != null">
                #{PRODUCTSMALLPIC,jdbcType=VARCHAR},
            </if>
            <if test="TS_PIC != null">
                #{TS_PIC,jdbcType=VARCHAR},
            </if>
            <if test="s_PIC != null">
                #{s_PIC,jdbcType=VARCHAR},
            </if>
            <if test="MS_PIC != null">
                #{MS_PIC,jdbcType=VARCHAR},
            </if>
            <if test="m_PIC != null">
                #{m_PIC,jdbcType=VARCHAR},
            </if>
            <if test="ML_PIC != null">
                #{ML_PIC,jdbcType=VARCHAR},
            </if>
            <if test="l_PIC != null">
                #{l_PIC,jdbcType=VARCHAR},
            </if>
            <if test="TL_PIC != null">
                #{TL_PIC,jdbcType=VARCHAR},
            </if>
        </trim>
    </insert>
    <update id="updateByPrimaryKeySelective" parameterType="com.bizwink.po.Column">
        <!--
          WARNING - @mbggenerated
          This element is automatically generated by MyBatis Generator, do not modify.
        -->
        update TBL_COLUMN
        <set>
            <if test="SITEID != null">
                SITEID = #{SITEID,jdbcType=DECIMAL},
            </if>
            <if test="PARENTID != null">
                PARENTID = #{PARENTID,jdbcType=DECIMAL},
            </if>
            <if test="ORDERID != null">
                ORDERID = #{ORDERID,jdbcType=DECIMAL},
            </if>
            <if test="CNAME != null">
                CNAME = #{CNAME,jdbcType=VARCHAR},
            </if>
            <if test="ENAME != null">
                ENAME = #{ENAME,jdbcType=VARCHAR},
            </if>
            <if test="DIRNAME != null">
                DIRNAME = #{DIRNAME,jdbcType=VARCHAR},
            </if>
            <if test="EDITOR != null">
                EDITOR = #{EDITOR,jdbcType=VARCHAR},
            </if>
            <if test="EXTNAME != null">
                EXTNAME = #{EXTNAME,jdbcType=VARCHAR},
            </if>
            <if test="CREATEDATE != null">
                CREATEDATE = #{CREATEDATE,jdbcType=DATE},
            </if>
            <if test="LASTUPDATED != null">
                LASTUPDATED = #{LASTUPDATED,jdbcType=DATE},
            </if>
            <if test="ISDEFINEATTR != null">
                ISDEFINEATTR = #{ISDEFINEATTR,jdbcType=DECIMAL},
            </if>
            <if test="HASARTICLEMODEL != null">
                HASARTICLEMODEL = #{HASARTICLEMODEL,jdbcType=DECIMAL},
            </if>
            <if test="ISAUDITED != null">
                ISAUDITED = #{ISAUDITED,jdbcType=DECIMAL},
            </if>
            <if test="ISPRODUCT != null">
                ISPRODUCT = #{ISPRODUCT,jdbcType=DECIMAL},
            </if>
            <if test="ISPUBLISHMORE != null">
                ISPUBLISHMORE = #{ISPUBLISHMORE,jdbcType=DECIMAL},
            </if>
            <if test="LANGUAGETYPE != null">
                LANGUAGETYPE = #{LANGUAGETYPE,jdbcType=DECIMAL},
            </if>
            <if test="COLUMNDESC != null">
                COLUMNDESC = #{COLUMNDESC,jdbcType=VARCHAR},
            </if>
            <if test="XMLTEMPLATE != null">
                XMLTEMPLATE = #{XMLTEMPLATE,jdbcType=VARCHAR},
            </if>
            <if test="CONTENTSHOWTYPE != null">
                CONTENTSHOWTYPE = #{CONTENTSHOWTYPE,jdbcType=DECIMAL},
            </if>
            <if test="ISRSS != null">
                ISRSS = #{ISRSS,jdbcType=DECIMAL},
            </if>
            <if test="GETRSSARTICLETIME != null">
                GETRSSARTICLETIME = #{GETRSSARTICLETIME,jdbcType=DECIMAL},
            </if>
            <if test="ARCHIVINGRULES != null">
                ARCHIVINGRULES = #{ARCHIVINGRULES,jdbcType=DECIMAL},
            </if>
            <if test="USEARTICLETYPE != null">
                USEARTICLETYPE = #{USEARTICLETYPE,jdbcType=DECIMAL},
            </if>
            <if test="ISTYPE != null">
                ISTYPE = #{ISTYPE,jdbcType=DECIMAL},
            </if>
            <if test="USERFLAG != null">
                USERFLAG = #{USERFLAG,jdbcType=DECIMAL},
            </if>
            <if test="USERLEVEL != null">
                USERLEVEL = #{USERLEVEL,jdbcType=DECIMAL},
            </if>
            <if test="SHAREFLAG != null">
                SHAREFLAG = #{SHAREFLAG,jdbcType=DECIMAL},
            </if>
            <if test="XMLTYPE != null">
                XMLTYPE = #{XMLTYPE,jdbcType=VARCHAR},
            </if>
            <if test="ARTICLECOUNT != null">
                ARTICLECOUNT = #{ARTICLECOUNT,jdbcType=DECIMAL},
            </if>
            <if test="PUBLICFLAG != null">
                PUBLICFLAG = #{PUBLICFLAG,jdbcType=DECIMAL},
            </if>
            <if test="TITLEPIC != null">
                TITLEPIC = #{TITLEPIC,jdbcType=VARCHAR},
            </if>
            <if test="VTITLEPIC != null">
                VTITLEPIC = #{VTITLEPIC,jdbcType=VARCHAR},
            </if>
            <if test="SOURCEPIC != null">
                SOURCEPIC = #{SOURCEPIC,jdbcType=VARCHAR},
            </if>
            <if test="AUTHORPIC != null">
                AUTHORPIC = #{AUTHORPIC,jdbcType=VARCHAR},
            </if>
            <if test="CONTENTPIC != null">
                CONTENTPIC = #{CONTENTPIC,jdbcType=VARCHAR},
            </if>
            <if test="SPECIALPIC != null">
                SPECIALPIC = #{SPECIALPIC,jdbcType=VARCHAR},
            </if>
            <if test="PRODUCTPIC != null">
                PRODUCTPIC = #{PRODUCTPIC,jdbcType=VARCHAR},
            </if>
            <if test="PRODUCTSMALLPIC != null">
                PRODUCTSMALLPIC = #{PRODUCTSMALLPIC,jdbcType=VARCHAR},
            </if>
            <if test="TS_PIC != null">
                TS_PIC = #{TS_PIC,jdbcType=VARCHAR},
            </if>
            <if test="s_PIC != null">
                S_PIC = #{s_PIC,jdbcType=VARCHAR},
            </if>
            <if test="MS_PIC != null">
                MS_PIC = #{MS_PIC,jdbcType=VARCHAR},
            </if>
            <if test="m_PIC != null">
                M_PIC = #{m_PIC,jdbcType=VARCHAR},
            </if>
            <if test="ML_PIC != null">
                ML_PIC = #{ML_PIC,jdbcType=VARCHAR},
            </if>
            <if test="l_PIC != null">
                L_PIC = #{l_PIC,jdbcType=VARCHAR},
            </if>
            <if test="TL_PIC != null">
                TL_PIC = #{TL_PIC,jdbcType=VARCHAR},
            </if>
        </set>
        where ID = #{ID,jdbcType=DECIMAL}
    </update>
    <update id="updateByPrimaryKey" parameterType="com.bizwink.po.Column">
        <!--
          WARNING - @mbggenerated
          This element is automatically generated by MyBatis Generator, do not modify.
        -->
        update TBL_COLUMN
        set SITEID = #{SITEID,jdbcType=DECIMAL},
        PARENTID = #{PARENTID,jdbcType=DECIMAL},
        ORDERID = #{ORDERID,jdbcType=DECIMAL},
        CNAME = #{CNAME,jdbcType=VARCHAR},
        ENAME = #{ENAME,jdbcType=VARCHAR},
        DIRNAME = #{DIRNAME,jdbcType=VARCHAR},
        EDITOR = #{EDITOR,jdbcType=VARCHAR},
        EXTNAME = #{EXTNAME,jdbcType=VARCHAR},
        CREATEDATE = #{CREATEDATE,jdbcType=DATE},
        LASTUPDATED = #{LASTUPDATED,jdbcType=DATE},
        ISDEFINEATTR = #{ISDEFINEATTR,jdbcType=DECIMAL},
        HASARTICLEMODEL = #{HASARTICLEMODEL,jdbcType=DECIMAL},
        ISAUDITED = #{ISAUDITED,jdbcType=DECIMAL},
        ISPRODUCT = #{ISPRODUCT,jdbcType=DECIMAL},
        ISPUBLISHMORE = #{ISPUBLISHMORE,jdbcType=DECIMAL},
        LANGUAGETYPE = #{LANGUAGETYPE,jdbcType=DECIMAL},
        COLUMNDESC = #{COLUMNDESC,jdbcType=VARCHAR},
        XMLTEMPLATE = #{XMLTEMPLATE,jdbcType=VARCHAR},
        CONTENTSHOWTYPE = #{CONTENTSHOWTYPE,jdbcType=DECIMAL},
        ISRSS = #{ISRSS,jdbcType=DECIMAL},
        GETRSSARTICLETIME = #{GETRSSARTICLETIME,jdbcType=DECIMAL},
        ARCHIVINGRULES = #{ARCHIVINGRULES,jdbcType=DECIMAL},
        USEARTICLETYPE = #{USEARTICLETYPE,jdbcType=DECIMAL},
        ISTYPE = #{ISTYPE,jdbcType=DECIMAL},
        USERFLAG = #{USERFLAG,jdbcType=DECIMAL},
        USERLEVEL = #{USERLEVEL,jdbcType=DECIMAL},
        SHAREFLAG = #{SHAREFLAG,jdbcType=DECIMAL},
        XMLTYPE = #{XMLTYPE,jdbcType=VARCHAR},
        ARTICLECOUNT = #{ARTICLECOUNT,jdbcType=DECIMAL},
        PUBLICFLAG = #{PUBLICFLAG,jdbcType=DECIMAL},
        TITLEPIC = #{TITLEPIC,jdbcType=VARCHAR},
        VTITLEPIC = #{VTITLEPIC,jdbcType=VARCHAR},
        SOURCEPIC = #{SOURCEPIC,jdbcType=VARCHAR},
        AUTHORPIC = #{AUTHORPIC,jdbcType=VARCHAR},
        CONTENTPIC = #{CONTENTPIC,jdbcType=VARCHAR},
        SPECIALPIC = #{SPECIALPIC,jdbcType=VARCHAR},
        PRODUCTPIC = #{PRODUCTPIC,jdbcType=VARCHAR},
        PRODUCTSMALLPIC = #{PRODUCTSMALLPIC,jdbcType=VARCHAR},
        TS_PIC = #{TS_PIC,jdbcType=VARCHAR},
        S_PIC = #{s_PIC,jdbcType=VARCHAR},
        MS_PIC = #{MS_PIC,jdbcType=VARCHAR},
        M_PIC = #{m_PIC,jdbcType=VARCHAR},
        ML_PIC = #{ML_PIC,jdbcType=VARCHAR},
        L_PIC = #{l_PIC,jdbcType=VARCHAR},
        TL_PIC = #{TL_PIC,jdbcType=VARCHAR}
        where ID = #{ID,jdbcType=DECIMAL}
    </update>

    <select id="getMajors" parameterType="java.util.Map" resultMap="BaseResultMap">
        <!--
          WARNING - @mbggenerated
          This element is automatically generated by MyBatis Generator, do not modify.
        -->
        select
        <include refid="Base_Column_List" />
        from TBL_COLUMN
        where PARENTID = #{parentId,jdbcType=DECIMAL}
        <if test="str!=null">
            and cname like CONCAT(CONCAT( '',#{str,jdbcType=VARCHAR}), '%')
        </if>
    </select>
</mapper>