<?xml version="1.0" encoding="UTF-8" ?>
<!DOCTYPE mapper PUBLIC "-//mybatis.org//DTD Mapper 3.0//EN" "http://mybatis.org/dtd/mybatis-3-mapper.dtd" >
<mapper namespace="com.bizwink.persistence.OrdersMapper" >
    <resultMap id="BaseResultMap" type="com.bizwink.po.Orders" >
        <!--
          WARNING - @mbggenerated
          This element is automatically generated by MyBatis Generator, do not modify.
        -->
        <id column="ID" property="ID" jdbcType="BIGINT" />
        <result column="ORDERID" property="ORDERID" jdbcType="BIGINT" />
        <result column="initorderid" property="initorderid" jdbcType="INTEGER" />
        <result column="USERID" property="USERID" jdbcType="INTEGER" />
        <result column="NAME" property="NAME" jdbcType="VARCHAR" />
        <result column="SEX" property="SEX" jdbcType="INTEGER" />
        <result column="ADDRESS" property="ADDRESS" jdbcType="VARCHAR" />
        <result column="POSTCODE" property="POSTCODE" jdbcType="VARCHAR" />
        <result column="PHONE" property="PHONE" jdbcType="VARCHAR" />
        <result column="TOTALFEE" property="TOTALFEE" jdbcType="DOUBLE" />
        <result column="DELIVERYFEE" property="DELIVERYFEE" jdbcType="DOUBLE" />
        <result column="PAYFEE" property="PAYFEE" jdbcType="DOUBLE" />
        <result column="VALID" property="VALID" jdbcType="INTEGER" />
        <result column="SITEID" property="SITEID" jdbcType="INTEGER" />
        <result column="STATUS" property="STATUS" jdbcType="INTEGER" />
        <result column="BILLINGWAY" property="BILLINGWAY" jdbcType="INTEGER" />
        <result column="CITY" property="CITY" jdbcType="VARCHAR" />
        <result column="RECEIVE" property="RECEIVE" jdbcType="INTEGER" />
        <result column="NOUSE" property="NOUSE" jdbcType="INTEGER" />
        <result column="PROVINCE" property="PROVINCE" jdbcType="VARCHAR" />
        <result column="zone" property="zone" jdbcType="VARCHAR" />
        <result column="sendway" property="sendway" jdbcType="INTEGER" />
        <result column="payway" property="payway" jdbcType="INTEGER" />
        <result column="commissioncharge" property="commissioncharge" jdbcType="DOUBLE" />
        <result column="insurance" property="insurance" jdbcType="DOUBLE" />
        <result column="need_invoice" property="need_invoice" jdbcType="INTEGER" />
        <result column="bill_to_address" property="bill_to_address" jdbcType="VARCHAR" />
        <result column="notes" property="notes" jdbcType="VARCHAR" />
        <result column="jylsh" property="jylsh" jdbcType="VARCHAR" />
        <result column="zfmemberid" property="zfmemberid" jdbcType="VARCHAR" />
        <result column="r2type" property="r2type" jdbcType="SMALLINT" />
        <result column="payresult" property="payresult" jdbcType="VARCHAR" />
        <result column="flag" property="flag" jdbcType="SMALLINT" />
        <result column="payflag" property="payflag" jdbcType="SMALLINT" />
        <result column="paycompno" property="paycompno" jdbcType="INTEGER" />
        <result column="linktime" property="linktime" jdbcType="VARCHAR" />
        <result column="usescores" property="usescores" jdbcType="INTEGER" />
        <result column="orderscores" property="orderscores" jdbcType="INTEGER" />
        <result column="CREATEDATE" property="CREATEDATE" jdbcType="TIMESTAMP" />
        <result column="paydate" property="paydate" jdbcType="TIMESTAMP" />
        <result column="lastupdate" property="lastupdate" jdbcType="TIMESTAMP" />
        <result column="projclassid" property="projclassid" jdbcType="INTEGER" />
        <result column="projartid" property="projartid" jdbcType="INTEGER" />
        <result column="projcode" property="projcode" jdbcType="VARCHAR" />
        <result column="majorcode" property="majorcode" jdbcType="VARCHAR" />
        <result column="projname" property="projname" jdbcType="VARCHAR" />
        <result column="trainunit" property="trainunit" jdbcType="VARCHAR" />
        <result column="projbrief" property="projbrief" jdbcType="VARCHAR" />
    </resultMap>
    <sql id="Base_Column_List" >
        <!--
          WARNING - @mbggenerated
          This element is automatically generated by MyBatis Generator, do not modify.
        -->
        ID,ORDERID, initorderid, USERID, NAME, SEX, ADDRESS, POSTCODE, PHONE, TOTALFEE, DELIVERYFEE,PAYFEE, CREATEDATE, VALID, SITEID, STATUS, BILLINGWAY, CITY, RECEIVE,
        NOUSE, PROVINCE,zone, sendway, payway, commissioncharge, insurance, need_invoice, bill_to_address,notes, jylsh, zfmemberid, r2type, payresult, flag, payflag,
        paycompno, linktime, usescores, orderscores,paydate,lastupdate,projclassid,projartid,projcode,majorcode,projname,trainunit,projbrief
    </sql>

    <select id="selectByPrimaryKey" resultMap="BaseResultMap" parameterType="java.lang.Long" >
        <!--
          WARNING - @mbggenerated
          This element is automatically generated by MyBatis Generator, do not modify.
        -->
        select
        <include refid="Base_Column_List" />
        from tbl_orders
        where ORDERID = #{ORDERID,jdbcType=BIGINT}
    </select>

    <select id="selectOrderCountByUid" resultType="java.lang.Integer" parameterType="java.lang.Integer" >
        <!--
          WARNING - @mbggenerated
          This element is automatically generated by MyBatis Generator, do not modify.
        -->
        select count(ID) from tbl_orders where USERID = #{USERID,jdbcType=INTEGER}
    </select>

    <select id="getOrderByUIDAndTraningProjcode" resultMap="BaseResultMap" parameterType="java.util.Map" >
        <!--
          WARNING - @mbggenerated
          This element is automatically generated by MyBatis Generator, do not modify.
        -->
        select
        <include refid="Base_Column_List" />
        from tbl_orders
        where USERID = #{USERID,jdbcType=DECIMAL} and  projartid=#{articleid,jdbcType=DECIMAL}
    </select>

    <select id="selectByUid" resultMap="BaseResultMap" parameterType="java.lang.Integer" >
        <!--
          WARNING - @mbggenerated
          This element is automatically generated by MyBatis Generator, do not modify.
        -->
        select
        <include refid="Base_Column_List" />
        from tbl_orders
        where USERID = #{USERID,jdbcType=INTEGER} order by CREATEDATE desc
    </select>

    <select id="selectByUidInPage" resultMap="BaseResultMap" parameterType="java.util.Map" >
        <!--
          WARNING - @mbggenerated
          This element is automatically generated by MyBatis Generator, do not modify.
        -->
        select * from (select tt.*, ROWNUM as rowno from (select <include refid="Base_Column_List" /> from tbl_orders t
        where SITEID = #{SITEID,jdbcType=DECIMAL} and USERID = #{UID,jdbcType=INTEGER}
        order by CREATEDATE desc) tt where ROWNUM &lt;= #{ENDROW,jdbcType=DECIMAL}) table_alias where table_alias.rowno &gt;= #{BEGINROW,jdbcType=DECIMAL}
    </select>

    <select id="getOrdersGreatTheOrderid" resultMap="BaseResultMap" parameterType="java.lang.Integer" >
        <!--
          WARNING - @mbggenerated
          This element is automatically generated by MyBatis Generator, do not modify.
        -->
        select
        <include refid="Base_Column_List" />
        from tbl_orders
        where ORDERID >= #{ORDERID,jdbcType=BIGINT}
    </select>

    <select id="getAllOrders" resultMap="BaseResultMap" >
        <!--
          WARNING - @mbggenerated
          This element is automatically generated by MyBatis Generator, do not modify.
        -->
        select
        <include refid="Base_Column_List" />
        from tbl_orders order by orderid desc
    </select>

    <delete id="deleteByPrimaryKey" parameterType="java.lang.Long" >
        <!--
          WARNING - @mbggenerated
          This element is automatically generated by MyBatis Generator, do not modify.
        -->
        delete from tbl_orders
        where ORDERID = #{ORDERID,jdbcType=BIGINT}
    </delete>



    <insert id="insert" useGeneratedKeys="true" keyColumn="ID" keyProperty="ID" parameterType="com.bizwink.po.Orders" databaseId="mysql">
        <!--
          WARNING - @mbggenerated
          This element is automatically generated by MyBatis Generator, do not modify.
        -->
        <selectKey resultType="long" keyProperty="ID" order="AFTER">
            SELECT LAST_INSERT_ID()
        </selectKey>

        insert into tbl_orders (ID,ORDERID,initorderid,USERID,NAME,SEX,ADDRESS,POSTCODE,PHONE,TOTALFEE,DELIVERYFEE,PAYFEE,CREATEDATE,lastupdate,VALID,SITEID,STATUS,
        BILLINGWAY,CITY,RECEIVE,NOUSE,PROVINCE,zone,sendway,payway,commissioncharge,insurance,need_invoice,bill_to_address,notes,jylsh,zfmemberid,r2type,
        payresult,flag,payflag,paycompno,linktime,usescores,orderscores,projclassid,projartid,projcode,majorcode,projname,trainunit,projbrief)
        values (#{ID,jdbcType=BIGINT},#{ORDERID,jdbcType=BIGINT}, #{initorderid,jdbcType=INTEGER}, #{USERID,jdbcType=INTEGER},#{NAME,jdbcType=VARCHAR},
        #{SEX,jdbcType=INTEGER}, #{ADDRESS,jdbcType=VARCHAR},#{POSTCODE,jdbcType=VARCHAR}, #{PHONE,jdbcType=VARCHAR}, #{TOTALFEE,jdbcType=DOUBLE},
        #{DELIVERYFEE,jdbcType=DOUBLE}, #{PAYFEE,jdbcType=DOUBLE}, #{CREATEDATE,jdbcType=TIMESTAMP},#{lastupdate,jdbcType=TIMESTAMP},#{VALID,jdbcType=INTEGER}, #{SITEID,jdbcType=INTEGER},
        #{STATUS,jdbcType=INTEGER},#{BILLINGWAY,jdbcType=INTEGER}, #{CITY,jdbcType=VARCHAR}, #{RECEIVE,jdbcType=INTEGER},#{NOUSE,jdbcType=INTEGER},
        #{PROVINCE,jdbcType=VARCHAR}, #{zone,jdbcType=VARCHAR},#{sendway,jdbcType=INTEGER}, #{payway,jdbcType=INTEGER}, #{commissioncharge,jdbcType=DOUBLE},
        #{insurance,jdbcType=DOUBLE}, #{need_invoice,jdbcType=INTEGER}, #{bill_to_address,jdbcType=VARCHAR},#{notes,jdbcType=VARCHAR},#{jylsh,jdbcType=VARCHAR},
        #{zfmemberid,jdbcType=VARCHAR},#{r2type,jdbcType=SMALLINT},#{payresult,jdbcType=VARCHAR},#{flag,jdbcType=SMALLINT}, #{payflag,jdbcType=SMALLINT},
        #{paycompno,jdbcType=INTEGER},#{linktime,jdbcType=VARCHAR}, #{usescores,jdbcType=INTEGER}, #{orderscores,jdbcType=INTEGER},#{projclassid,jdbcType=INTEGER},
        #{projartid,jdbcType=INTEGER},#{projcode,jdbcType=VARCHAR},#{majorcode,jdbcType=VARCHAR},#{projname,jdbcType=VARCHAR},#{trainunit,jdbcType=VARCHAR},
        #{projbrief,jdbcType=VARCHAR}
        )
    </insert>

    <insert id="insert" useGeneratedKeys="true" keyColumn="ID" keyProperty="ID" parameterType="com.bizwink.po.Orders"  databaseId="oracle">
        <!--
          WARNING - @mbggenerated
          This element is automatically generated by MyBatis Generator, do not modify.
        -->
        <selectKey  keyProperty="ID" resultType="long" order="BEFORE">
            select TBL_ORDERS_DETAIL_ID.NEXTVAL from dual
        </selectKey>

        insert into tbl_orders (ID,ORDERID,initorderid,USERID,NAME,SEX,ADDRESS,POSTCODE,PHONE,TOTALFEE,DELIVERYFEE,PAYFEE,CREATEDATE,lastupdate,VALID,SITEID,STATUS,
        BILLINGWAY,CITY,RECEIVE,NOUSE,PROVINCE,zone,sendway,payway,commissioncharge,insurance,need_invoice,bill_to_address,notes,jylsh,zfmemberid,r2type,
        payresult,flag,payflag,paycompno,linktime,usescores,orderscores,projclassid,projartid,projcode,majorcode,projname,trainunit,projbrief)
        values (#{ID,jdbcType=BIGINT},#{ORDERID,jdbcType=BIGINT}, #{initorderid,jdbcType=INTEGER}, #{USERID,jdbcType=INTEGER},#{NAME,jdbcType=VARCHAR},
        #{SEX,jdbcType=INTEGER}, #{ADDRESS,jdbcType=VARCHAR},#{POSTCODE,jdbcType=VARCHAR}, #{PHONE,jdbcType=VARCHAR}, #{TOTALFEE,jdbcType=DOUBLE},
        #{DELIVERYFEE,jdbcType=DOUBLE}, #{PAYFEE,jdbcType=DOUBLE}, #{CREATEDATE,jdbcType=TIMESTAMP},#{lastupdate,jdbcType=TIMESTAMP},#{VALID,jdbcType=INTEGER}, #{SITEID,jdbcType=INTEGER},
        #{STATUS,jdbcType=INTEGER},#{BILLINGWAY,jdbcType=INTEGER}, #{CITY,jdbcType=VARCHAR}, #{RECEIVE,jdbcType=INTEGER},#{NOUSE,jdbcType=INTEGER},
        #{PROVINCE,jdbcType=VARCHAR}, #{zone,jdbcType=VARCHAR},#{sendway,jdbcType=INTEGER}, #{payway,jdbcType=INTEGER}, #{commissioncharge,jdbcType=DOUBLE},
        #{insurance,jdbcType=DOUBLE}, #{need_invoice,jdbcType=INTEGER},#{bill_to_address,jdbcType=VARCHAR},#{notes,jdbcType=VARCHAR},#{jylsh,jdbcType=VARCHAR},
        #{zfmemberid,jdbcType=VARCHAR},#{r2type,jdbcType=SMALLINT},#{payresult,jdbcType=VARCHAR},#{flag,jdbcType=SMALLINT}, #{payflag,jdbcType=SMALLINT},
        #{paycompno,jdbcType=INTEGER},#{linktime,jdbcType=VARCHAR},#{usescores,jdbcType=INTEGER},#{orderscores,jdbcType=INTEGER},#{projclassid,jdbcType=INTEGER},
        #{projartid,jdbcType=INTEGER},#{projcode,jdbcType=VARCHAR},#{majorcode,jdbcType=VARCHAR},#{projname,jdbcType=VARCHAR},#{trainunit,jdbcType=VARCHAR},
        #{projbrief,jdbcType=VARCHAR}
        )
    </insert>

    <insert id="insertSelective" parameterType="com.bizwink.po.Orders" >
        <!--
          WARNING - @mbggenerated
          This element is automatically generated by MyBatis Generator, do not modify.
        -->
        insert into tbl_orders
        <trim prefix="(" suffix=")" suffixOverrides="," >
            <if test="ID != null" >
                ID,
            </if>
            <if test="ORDERID != null" >
                ORDERID,
            </if>
            <if test="initorderid != null" >
                initorderid,
            </if>
            <if test="USERID != null" >
                USERID,
            </if>
            <if test="NAME != null" >
                NAME,
            </if>
            <if test="SEX != null" >
                SEX,
            </if>
            <if test="ADDRESS != null" >
                ADDRESS,
            </if>
            <if test="POSTCODE != null" >
                POSTCODE,
            </if>
            <if test="PHONE != null" >
                PHONE,
            </if>
            <if test="TOTALFEE != null" >
                TOTALFEE,
            </if>
            <if test="DELIVERYFEE != null" >
                DELIVERYFEE,
            </if>
            <if test="PAYFEE != null" >
                PAYFEE,
            </if>
            <if test="CREATEDATE != null" >
                CREATEDATE,
            </if>
            <if test="VALID != null" >
                VALID,
            </if>
            <if test="SITEID != null" >
                SITEID,
            </if>
            <if test="STATUS != null" >
                STATUS,
            </if>
            <if test="BILLINGWAY != null" >
                BILLINGWAY,
            </if>
            <if test="CITY != null" >
                CITY,
            </if>
            <if test="RECEIVE != null" >
                RECEIVE,
            </if>
            <if test="NOUSE != null" >
                NOUSE,
            </if>
            <if test="PROVINCE != null" >
                PROVINCE,
            </if>
            <if test="zone != null" >
                zone,
            </if>
            <if test="sendway != null" >
                sendway,
            </if>
            <if test="payway != null" >
                payway,
            </if>
            <if test="commissioncharge != null" >
                commissioncharge,
            </if>
            <if test="insurance != null" >
                insurance,
            </if>
            <if test="need_invoice != null" >
                need_invoice,
            </if>
            <if test="bill_to_address != null" >
                bill_to_address,
            </if>
            <if test="notes != null" >
                notes,
            </if>
            <if test="jylsh != null" >
                jylsh,
            </if>
            <if test="flag != null" >
                flag,
            </if>
            <if test="payflag != null" >
                payflag,
            </if>
            <if test="paycompno != null" >
                paycompno,
            </if>
            <if test="linktime != null" >
                linktime,
            </if>
            <if test="usescores != null" >
                usescores,
            </if>
            <if test="orderscores != null" >
                orderscores,
            </if>
            <if test="paydate != null" >
                paydate,
            </if>
            <if test="lastupdate != null" >
                lastupdate,
            </if>
            <if test="projclassid != null" >
                projclassid,
            </if>
            <if test="projartid != null" >
                projartid,
            </if>
            <if test="projcode != null" >
                projcode,
            </if>
            <if test="majorcode != null" >
                majorcode,
            </if>
            <if test="projname != null" >
                projname,
            </if>
            <if test="trainunit != null" >
                trainunit,
            </if>
            <if test="projbrief != null" >
                projbrief,
            </if>
        </trim>
        <trim prefix="values (" suffix=")" suffixOverrides="," >
            <if test="ID != null" >
                #{ID,jdbcType=BIGINT},
            </if>
            <if test="ORDERID != null" >
                #{ORDERID,jdbcType=BIGINT},
            </if>
            <if test="initorderid != null" >
                #{initorderid,jdbcType=INTEGER},
            </if>
            <if test="USERID != null" >
                #{USERID,jdbcType=INTEGER},
            </if>
            <if test="NAME != null" >
                #{NAME,jdbcType=VARCHAR},
            </if>
            <if test="SEX != null" >
                #{SEX,jdbcType=INTEGER},
            </if>
            <if test="ADDRESS != null" >
                #{ADDRESS,jdbcType=VARCHAR},
            </if>
            <if test="POSTCODE != null" >
                #{POSTCODE,jdbcType=VARCHAR},
            </if>
            <if test="PHONE != null" >
                #{PHONE,jdbcType=VARCHAR},
            </if>
            <if test="TOTALFEE != null" >
                #{TOTALFEE,jdbcType=DOUBLE},
            </if>
            <if test="DELIVERYFEE != null" >
                #{DELIVERYFEE,jdbcType=DOUBLE},
            </if>
            <if test="PAYFEE != null" >
                #{PAYFEE,jdbcType=DOUBLE},
            </if>
            <if test="CREATEDATE != null" >
                #{CREATEDATE,jdbcType=TIMESTAMP},
            </if>
            <if test="VALID != null" >
                #{VALID,jdbcType=INTEGER},
            </if>
            <if test="SITEID != null" >
                #{SITEID,jdbcType=INTEGER},
            </if>
            <if test="STATUS != null" >
                #{STATUS,jdbcType=INTEGER},
            </if>
            <if test="BILLINGWAY != null" >
                #{BILLINGWAY,jdbcType=INTEGER},
            </if>
            <if test="CITY != null" >
                #{CITY,jdbcType=VARCHAR},
            </if>
            <if test="RECEIVE != null" >
                #{RECEIVE,jdbcType=INTEGER},
            </if>
            <if test="NOUSE != null" >
                #{NOUSE,jdbcType=INTEGER},
            </if>
            <if test="PROVINCE != null" >
                #{PROVINCE,jdbcType=VARCHAR},
            </if>
            <if test="zone != null" >
                #{zone,jdbcType=VARCHAR},
            </if>
            <if test="sendway != null" >
                #{sendway,jdbcType=INTEGER},
            </if>
            <if test="payway != null" >
                #{payway,jdbcType=INTEGER},
            </if>
            <if test="commissioncharge != null" >
                #{commissioncharge,jdbcType=DOUBLE},
            </if>
            <if test="insurance != null" >
                #{insurance,jdbcType=DOUBLE},
            </if>
            <if test="need_invoice != null" >
                #{need_invoice,jdbcType=INTEGER},
            </if>
            <if test="bill_to_address != null" >
                #{bill_to_address,jdbcType=VARCHAR},
            </if>
            <if test="notes != null" >
                #{notes,jdbcType=VARCHAR},
            </if>
            <if test="jylsh != null" >
                #{jylsh,jdbcType=VARCHAR},
            </if>
            <if test="flag != null" >
                #{flag,jdbcType=SMALLINT},
            </if>
            <if test="payflag != null" >
                #{payflag,jdbcType=SMALLINT},
            </if>
            <if test="paycompno != null" >
                #{paycompno,jdbcType=INTEGER},
            </if>
            <if test="linktime != null" >
                #{linktime,jdbcType=VARCHAR},
            </if>
            <if test="usescores != null" >
                #{usescores,jdbcType=INTEGER},
            </if>
            <if test="orderscores != null" >
                #{orderscores,jdbcType=INTEGER},
            </if>
            <if test="paydate != null" >
                #{paydate,jdbcType=TIMESTAMP},
            </if>
            <if test="lastupdate != null" >
                #{lastupdate,jdbcType=TIMESTAMP},
            </if>
            <if test="projclassid != null" >
                #{projclassid,jdbcType=INTEGER},
            </if>
            <if test="projartid != null" >
                #{projartid,jdbcType=INTEGER},
            </if>
            <if test="projcode != null" >
                #{projcode,jdbcType=VARCHAR},
            </if>
            <if test="majorcode != null" >
                #{majorcode,jdbcType=VARCHAR},
            </if>
            <if test="projname != null" >
                #{projname,jdbcType=VARCHAR},
            </if>
            <if test="trainunit != null" >
                #{trainunit,jdbcType=VARCHAR},
            </if>
            <if test="projbrief != null" >
                #{projbrief,jdbcType=VARCHAR},
            </if>
        </trim>
    </insert>

    <update id="updateByPrimaryKeySelective" parameterType="com.bizwink.po.Orders" >
        <!--
          WARNING - @mbggenerated
          This element is automatically generated by MyBatis Generator, do not modify.
        -->
        update tbl_orders
        <set >
            <if test="initorderid != null" >
                initorderid = #{initorderid,jdbcType=INTEGER},
            </if>
            <if test="USERID != null" >
                USERID = #{USERID,jdbcType=INTEGER},
            </if>
            <if test="NAME != null" >
                NAME = #{NAME,jdbcType=VARCHAR},
            </if>
            <if test="SEX != null" >
                SEX = #{SEX,jdbcType=INTEGER},
            </if>
            <if test="ADDRESS != null" >
                ADDRESS = #{ADDRESS,jdbcType=VARCHAR},
            </if>
            <if test="POSTCODE != null" >
                POSTCODE = #{POSTCODE,jdbcType=VARCHAR},
            </if>
            <if test="PHONE != null" >
                PHONE = #{PHONE,jdbcType=VARCHAR},
            </if>
            <if test="TOTALFEE != null" >
                TOTALFEE = #{TOTALFEE,jdbcType=DOUBLE},
            </if>
            <if test="DELIVERYFEE != null" >
                DELIVERYFEE = #{DELIVERYFEE,jdbcType=DOUBLE},
            </if>
            <if test="PAYFEE != null" >
                PAYFEE = #{PAYFEE,jdbcType=DOUBLE},
            </if>
            <if test="CREATEDATE != null" >
                CREATEDATE = #{CREATEDATE,jdbcType=TIMESTAMP},
            </if>
            <if test="VALID != null" >
                VALID = #{VALID,jdbcType=INTEGER},
            </if>
            <if test="SITEID != null" >
                SITEID = #{SITEID,jdbcType=INTEGER},
            </if>
            <if test="STATUS != null" >
                STATUS = #{STATUS,jdbcType=INTEGER},
            </if>
            <if test="BILLINGWAY != null" >
                BILLINGWAY = #{BILLINGWAY,jdbcType=INTEGER},
            </if>
            <if test="CITY != null" >
                CITY = #{CITY,jdbcType=VARCHAR},
            </if>
            <if test="RECEIVE != null" >
                RECEIVE = #{RECEIVE,jdbcType=INTEGER},
            </if>
            <if test="NOUSE != null" >
                NOUSE = #{NOUSE,jdbcType=INTEGER},
            </if>
            <if test="PROVINCE != null" >
                PROVINCE = #{PROVINCE,jdbcType=VARCHAR},
            </if>
            <if test="zone != null" >
                zone = #{zone,jdbcType=VARCHAR},
            </if>
            <if test="sendway != null" >
                sendway = #{sendway,jdbcType=INTEGER},
            </if>
            <if test="payway != null" >
                payway = #{payway,jdbcType=INTEGER},
            </if>
            <if test="commissioncharge != null" >
                commissioncharge = #{commissioncharge,jdbcType=DOUBLE},
            </if>
            <if test="insurance != null" >
                insurance = #{insurance,jdbcType=DOUBLE},
            </if>
            <if test="need_invoice != null" >
                need_invoice = #{need_invoice,jdbcType=INTEGER},
            </if>
            <if test="bill_to_address != null" >
                bill_to_address = #{bill_to_address,jdbcType=VARCHAR},
            </if>
            <if test="notes != null" >
                notes = #{notes,jdbcType=VARCHAR},
            </if>
            <if test="jylsh != null" >
                jylsh = #{jylsh,jdbcType=VARCHAR},
            </if>
            <if test="flag != null" >
                flag = #{flag,jdbcType=SMALLINT},
            </if>
            <if test="payflag != null" >
                payflag = #{payflag,jdbcType=SMALLINT},
            </if>
            <if test="paycompno != null" >
                paycompno = #{paycompno,jdbcType=INTEGER},
            </if>
            <if test="linktime != null" >
                linktime = #{linktime,jdbcType=VARCHAR},
            </if>
            <if test="usescores != null" >
                usescores = #{usescores,jdbcType=INTEGER},
            </if>
            <if test="orderscores != null" >
                orderscores = #{orderscores,jdbcType=INTEGER},
            </if>
            <if test="paydate != null" >
                paydate = #{paydate,jdbcType=TIMESTAMP},
            </if>
            <if test="lastupdate != null" >
                lastupdate = #{lastupdate,jdbcType=TIMESTAMP},
            </if>
            <if test="projclassid != null" >
                projclassid = #{projclassid,jdbcType=INTEGER},
            </if>
            <if test="projartid != null" >
                projartid = #{projartid,jdbcType=INTEGER},
            </if>
            <if test="projcode != null" >
                projcode = #{projcode,jdbcType=VARCHAR},
            </if>
            <if test="majorcode != null" >
                majorcode = #{majorcode,jdbcType=VARCHAR},
            </if>
            <if test="projname != null" >
                projname = #{projname,jdbcType=VARCHAR},
            </if>
            <if test="trainunit != null" >
                trainunit = #{trainunit,jdbcType=VARCHAR},
            </if>
            <if test="projbrief != null" >
                projbrief = #{projbrief,jdbcType=VARCHAR},
            </if>
        </set>
        where ORDERID = #{ORDERID,jdbcType=BIGINT}
    </update>
    <update id="updatePayflag" parameterType="com.bizwink.po.Orders" >
        <!--
          WARNING - @mbggenerated
          This element is automatically generated by MyBatis Generator, do not modify.
        -->
        update tbl_orders
        set payflag = #{payflag,jdbcType=SMALLINT},
        paydate = #{paydate,jdbcType=TIMESTAMP},
        jylsh = #{jylsh,jdbcType=VARCHAR},
        zfmemberid = #{zfmemberid,jdbcType=VARCHAR},
        r2type = #{r2type,jdbcType=SMALLINT},
        payresult = #{payresult,jdbcType=VARCHAR},
        payway = #{payway,jdbcType=INTEGER},
        STATUS = #{STATUS,jdbcType=SMALLINT}
        where ORDERID = #{ORDERID,jdbcType=BIGINT}
    </update>

    <update id="updateStatus" parameterType="com.bizwink.po.Orders" >
        <!--
          WARNING - @mbggenerated
          This element is automatically generated by MyBatis Generator, do not modify.
        -->
        update tbl_orders
        set lastupdate = #{lastupdate,jdbcType=TIMESTAMP},
        STATUS = #{STATUS,jdbcType=SMALLINT}
        where ORDERID = #{ORDERID,jdbcType=BIGINT}
    </update>

    <update id="updateByPrimaryKey" parameterType="com.bizwink.po.Orders" >
        <!--
          WARNING - @mbggenerated
          This element is automatically generated by MyBatis Generator, do not modify.
        -->
        update tbl_orders
        set initorderid = #{initorderid,jdbcType=INTEGER},
        USERID = #{USERID,jdbcType=INTEGER},
        NAME = #{NAME,jdbcType=VARCHAR},
        SEX = #{SEX,jdbcType=INTEGER},
        ADDRESS = #{ADDRESS,jdbcType=VARCHAR},
        POSTCODE = #{POSTCODE,jdbcType=VARCHAR},
        PHONE = #{PHONE,jdbcType=VARCHAR},
        TOTALFEE = #{TOTALFEE,jdbcType=DOUBLE},
        DELIVERYFEE = #{DELIVERYFEE,jdbcType=DOUBLE},
        PAYFEE = #{PAYFEE,jdbcType=DOUBLE},
        CREATEDATE = #{CREATEDATE,jdbcType=TIMESTAMP},
        VALID = #{VALID,jdbcType=INTEGER},
        SITEID = #{SITEID,jdbcType=INTEGER},
        STATUS = #{STATUS,jdbcType=INTEGER},
        BILLINGWAY = #{BILLINGWAY,jdbcType=INTEGER},
        CITY = #{CITY,jdbcType=VARCHAR},
        RECEIVE = #{RECEIVE,jdbcType=INTEGER},
        NOUSE = #{NOUSE,jdbcType=INTEGER},
        PROVINCE = #{PROVINCE,jdbcType=VARCHAR},
        zone = #{zone,jdbcType=VARCHAR},
        sendway = #{sendway,jdbcType=INTEGER},
        payway = #{payway,jdbcType=INTEGER},
        commissioncharge = #{commissioncharge,jdbcType=DOUBLE},
        insurance = #{insurance,jdbcType=DOUBLE},
        need_invoice = #{need_invoice,jdbcType=INTEGER},
        bill_to_address = #{bill_to_address,jdbcType=VARCHAR},
        notes = #{notes,jdbcType=VARCHAR},
        jylsh = #{jylsh,jdbcType=VARCHAR},
        flag = #{flag,jdbcType=SMALLINT},
        payflag = #{payflag,jdbcType=SMALLINT},
        paycompno = #{paycompno,jdbcType=INTEGER},
        linktime = #{linktime,jdbcType=VARCHAR},
        usescores = #{usescores,jdbcType=INTEGER},
        orderscores = #{orderscores,jdbcType=INTEGER}
        paydate = #{paydate,jdbcType=TIMESTAMP}
        lastupdate = #{lastupdate,jdbcType=TIMESTAMP}
        projclassid = #{projclassid,jdbcType=INTEGER}
        projartid = #{projartid,jdbcType=INTEGER}
        projcode = #{projcode,jdbcType=VARCHAR},
        majorcode = #{majorcode,jdbcType=VARCHAR},
        projname = #{projname,jdbcType=VARCHAR},
        trainunit = #{trainunit,jdbcType=VARCHAR},
        projbrief = #{projbrief,jdbcType=VARCHAR},
        where ORDERID = #{ORDERID,jdbcType=BIGINT}
    </update>
</mapper>